{
  "version": "https://jsonfeed.org/version/1",
  "title": "Grab Tech",
  "description": "Grab's Engineering team solves critical transportation challenges and makes transport freedom a reality for 620 million people in Southeast Asia.\n",
  "home_page_url": "https://engineering.grab.com",
  "feed_url": "https://engineering.grab.com/feed.json",
  "favicon": "https://engineering.grab.com/favicon.png",
  
  "items": [

    
    {
      "id": "https://engineering.grab.com/reshaping-chat-support",
      "url": "https://engineering.grab.com/reshaping-chat-support",
      "title": "Reshaping Chat Support for Our Users",
      "date_published": "Wed, 07 Jul 2021 00:18:20 +0000",
      "authors": [
        
          
          "Elisa Monacchi"
          ,
        
          
          "Wan Ling Guai"
          ,
        
          
          "Suman Anand"
          
        
      ]
    }
    ,
    
    {
      "id": "https://engineering.grab.com/debugging-high-latency-market-store",
      "url": "https://engineering.grab.com/debugging-high-latency-market-store",
      "title": "Debugging High Latency Due to Context Leaks",
      "date_published": "Wed, 30 Jun 2021 00:08:20 +0000",
      "authors": [
        
          
          "Sourabh Suman"
          ,
        
          
          "Adarsh Koyya"
          ,
        
          
          "ChandanKumar Agarwal"
          
        
      ]
    }
    ,
    
    {
      "id": "https://engineering.grab.com/building-hyper-self-service-distributed-tracing-feedback-system",
      "url": "https://engineering.grab.com/building-hyper-self-service-distributed-tracing-feedback-system",
      "title": "Building a Hyper Self-Service, Distributed Tracing and Feedback System for Rule & Machine Learning (ML) Predictions",
      "date_published": "Mon, 24 May 2021 00:11:20 +0000",
      "authors": [
        
          
          "Warren Zhou"
          ,
        
          
          "Wenhui Wu"
          ,
        
          
          "Yongguo Mei"
          ,
        
          
          "Muqi Li"
          ,
        
          
          "Varun Kansal"
          
        
      ]
    }
    ,
    
    {
      "id": "https://engineering.grab.com/our-journey-to-continuous-delivery-at-grab-part2",
      "url": "https://engineering.grab.com/our-journey-to-continuous-delivery-at-grab-part2",
      "title": "Our Journey to Continuous Delivery at Grab (Part 2)",
      "date_published": "Mon, 10 May 2021 08:10:20 +0000",
      "authors": [
        
          
          "Sylvain Bougerel"
          
        
      ]
    }
    ,
    
    {
      "id": "https://engineering.grab.com/how-we-improved-agent-chat-efficiency-with-ml",
      "url": "https://engineering.grab.com/how-we-improved-agent-chat-efficiency-with-ml",
      "title": "How We Improved Agent Chat Efficiency with Machine Learning",
      "date_published": "Mon, 19 Apr 2021 00:08:30 +0000",
      "authors": [
        
          
          "Suman Anand"
          ,
        
          
          "Elisa Monacchi"
          ,
        
          
          "Darrell Tay"
          ,
        
          
          "Yun Zou"
          ,
        
          
          "Wan Ling Guai"
          
        
      ]
    }
    ,
    
    {
      "id": "https://engineering.grab.com/learn-how-grab-leveraged-performance-marketing-automation",
      "url": "https://engineering.grab.com/learn-how-grab-leveraged-performance-marketing-automation",
      "title": "How Grab Leveraged Performance Marketing Automation to Improve Conversion Rates by 30%",
      "date_published": "Mon, 22 Mar 2021 00:13:30 +0000",
      "authors": [
        
          
          "Sc Ng"
          ,
        
          
          "Herman Khoo"
          ,
        
          
          "Audrey Jee"
          ,
        
          
          "Vaibhav Vij"
          ,
        
          
          "Mohammed Milhad Miah"
          
        
      ]
    }
    ,
    
    {
      "id": "https://engineering.grab.com/reducing-your-go-binary-size",
      "url": "https://engineering.grab.com/reducing-your-go-binary-size",
      "title": "One Small Step Closer to Containerising Service Binaries",
      "date_published": "Tue, 23 Feb 2021 00:12:23 +0000",
      "authors": [
        
          
          "Stan Halka"
          ,
        
          
          "Samuel Thomas"
          
        
      ]
    }
    ,
    
    {
      "id": "https://engineering.grab.com/customer-support-workforce-routing",
      "url": "https://engineering.grab.com/customer-support-workforce-routing",
      "title": "Customer Support Workforce Routing",
      "date_published": "Fri, 05 Feb 2021 00:15:00 +0000",
      "authors": [
        
          
          "Suman Anand"
          ,
        
          
          "Elisa Monacchi"
          ,
        
          
          "Jasmine Lim"
          ,
        
          
          "Matthew Yeow"
          ,
        
          
          "Pengcheng Zhao"
          
        
      ]
    }
    ,
    
    {
      "id": "https://engineering.grab.com/mirror-cache-blog",
      "url": "https://engineering.grab.com/mirror-cache-blog",
      "title": "Serving Driver-partners Data at Scale Using Mirror Cache",
      "date_published": "Tue, 26 Jan 2021 00:23:00 +0000",
      "authors": [
        
          
          "Indrajit Sarkar"
          
        
      ]
    }
    ,
    
    {
      "id": "https://engineering.grab.com/grabmart-product-team-experience",
      "url": "https://engineering.grab.com/grabmart-product-team-experience",
      "title": "The GrabMart Journey",
      "date_published": "Mon, 18 Jan 2021 03:23:00 +0000",
      "authors": [
        
          
          "Clarisse Peralta"
          ,
        
          
          "Shweta Padmanaban"
          ,
        
          
          "Ya Gao"
          ,
        
          
          "Eelin Ngiow"
          
        
      ]
    }
    
    
  ]
}